Metadata-Version: 1.1
Name: hctextshow
Version: 0.0.1
Summary: 红茶工作室与红茶·月夜发布的终端输出库
Home-page: https://github.com/
Author: haowen zhang
Author-email: 806670753@qq.com
License: UNKNOWN
Platform: UNKNOWN
Classifier: Programming Language :: Python :: 3
Classifier: License :: OSI Approved :: MIT License
Classifier: Operating System :: OS Independent
